<?xml version="1.0" encoding="UTF-8" standalone="yes"?>
<template encoding-version="1.2">
    <description></description>
    <groupId>2085f647-017d-1000-ffff-fffff1dbeec7</groupId>
    <name>Base SCB</name>
    <snippet>
        <connections>
            <id>507f7a1a-933d-3632-0000-000000000000</id>
            <parentGroupId>8414dd68-5e91-3e41-0000-000000000000</parentGroupId>
            <backPressureDataSizeThreshold>1 GB</backPressureDataSizeThreshold>
            <backPressureObjectThreshold>10000</backPressureObjectThreshold>
            <destination>
                <groupId>8414dd68-5e91-3e41-0000-000000000000</groupId>
                <id>b41c46dd-d05f-3ce1-0000-000000000000</id>
                <type>PROCESSOR</type>
            </destination>
            <flowFileExpiration>0 sec</flowFileExpiration>
            <labelIndex>1</labelIndex>
            <loadBalanceCompression>DO_NOT_COMPRESS</loadBalanceCompression>
            <loadBalancePartitionAttribute></loadBalancePartitionAttribute>
            <loadBalanceStatus>LOAD_BALANCE_NOT_CONFIGURED</loadBalanceStatus>
            <loadBalanceStrategy>DO_NOT_LOAD_BALANCE</loadBalanceStrategy>
            <name></name>
            <selectedRelationships>success</selectedRelationships>
            <source>
                <groupId>8414dd68-5e91-3e41-0000-000000000000</groupId>
                <id>03374573-a857-37f2-0000-000000000000</id>
                <type>PROCESSOR</type>
            </source>
            <zIndex>0</zIndex>
        </connections>
        <connections>
            <id>5571a9a0-ef9d-3c83-0000-000000000000</id>
            <parentGroupId>8414dd68-5e91-3e41-0000-000000000000</parentGroupId>
            <backPressureDataSizeThreshold>1 GB</backPressureDataSizeThreshold>
            <backPressureObjectThreshold>10000</backPressureObjectThreshold>
            <destination>
                <groupId>8414dd68-5e91-3e41-0000-000000000000</groupId>
                <id>e8752c00-55fa-3568-0000-000000000000</id>
                <type>PROCESSOR</type>
            </destination>
            <flowFileExpiration>0 sec</flowFileExpiration>
            <labelIndex>1</labelIndex>
            <loadBalanceCompression>DO_NOT_COMPRESS</loadBalanceCompression>
            <loadBalancePartitionAttribute></loadBalancePartitionAttribute>
            <loadBalanceStatus>LOAD_BALANCE_NOT_CONFIGURED</loadBalanceStatus>
            <loadBalanceStrategy>DO_NOT_LOAD_BALANCE</loadBalanceStrategy>
            <name></name>
            <selectedRelationships>success</selectedRelationships>
            <source>
                <groupId>8414dd68-5e91-3e41-0000-000000000000</groupId>
                <id>0fecae58-a198-382f-0000-000000000000</id>
                <type>PROCESSOR</type>
            </source>
            <zIndex>0</zIndex>
        </connections>
        <connections>
            <id>61b7c658-fd74-3a11-0000-000000000000</id>
            <parentGroupId>8414dd68-5e91-3e41-0000-000000000000</parentGroupId>
            <backPressureDataSizeThreshold>1 GB</backPressureDataSizeThreshold>
            <backPressureObjectThreshold>10000</backPressureObjectThreshold>
            <destination>
                <groupId>8414dd68-5e91-3e41-0000-000000000000</groupId>
                <id>22ba0944-f05e-3ddf-0000-000000000000</id>
                <type>PROCESSOR</type>
            </destination>
            <flowFileExpiration>0 sec</flowFileExpiration>
            <labelIndex>1</labelIndex>
            <loadBalanceCompression>DO_NOT_COMPRESS</loadBalanceCompression>
            <loadBalancePartitionAttribute></loadBalancePartitionAttribute>
            <loadBalanceStatus>LOAD_BALANCE_NOT_CONFIGURED</loadBalanceStatus>
            <loadBalanceStrategy>DO_NOT_LOAD_BALANCE</loadBalanceStrategy>
            <name></name>
            <source>
                <groupId>8414dd68-5e91-3e41-0000-000000000000</groupId>
                <id>a21aca55-f7be-31ea-0000-000000000000</id>
                <type>FUNNEL</type>
            </source>
            <zIndex>0</zIndex>
        </connections>
        <connections>
            <id>8958bd60-2eb8-3c16-0000-000000000000</id>
            <parentGroupId>8414dd68-5e91-3e41-0000-000000000000</parentGroupId>
            <backPressureDataSizeThreshold>1 GB</backPressureDataSizeThreshold>
            <backPressureObjectThreshold>10000</backPressureObjectThreshold>
            <destination>
                <groupId>8414dd68-5e91-3e41-0000-000000000000</groupId>
                <id>03374573-a857-37f2-0000-000000000000</id>
                <type>PROCESSOR</type>
            </destination>
            <flowFileExpiration>0 sec</flowFileExpiration>
            <labelIndex>1</labelIndex>
            <loadBalanceCompression>DO_NOT_COMPRESS</loadBalanceCompression>
            <loadBalancePartitionAttribute></loadBalancePartitionAttribute>
            <loadBalanceStatus>LOAD_BALANCE_NOT_CONFIGURED</loadBalanceStatus>
            <loadBalanceStrategy>DO_NOT_LOAD_BALANCE</loadBalanceStrategy>
            <name></name>
            <selectedRelationships>unmatched</selectedRelationships>
            <source>
                <groupId>8414dd68-5e91-3e41-0000-000000000000</groupId>
                <id>8494b873-005f-33d9-0000-000000000000</id>
                <type>PROCESSOR</type>
            </source>
            <zIndex>0</zIndex>
        </connections>
        <connections>
            <id>930c23f0-3ba5-301f-0000-000000000000</id>
            <parentGroupId>8414dd68-5e91-3e41-0000-000000000000</parentGroupId>
            <backPressureDataSizeThreshold>1 GB</backPressureDataSizeThreshold>
            <backPressureObjectThreshold>10000</backPressureObjectThreshold>
            <destination>
                <groupId>8414dd68-5e91-3e41-0000-000000000000</groupId>
                <id>a21aca55-f7be-31ea-0000-000000000000</id>
                <type>FUNNEL</type>
            </destination>
            <flowFileExpiration>0 sec</flowFileExpiration>
            <labelIndex>1</labelIndex>
            <loadBalanceCompression>DO_NOT_COMPRESS</loadBalanceCompression>
            <loadBalancePartitionAttribute></loadBalancePartitionAttribute>
            <loadBalanceStatus>LOAD_BALANCE_NOT_CONFIGURED</loadBalanceStatus>
            <loadBalanceStrategy>DO_NOT_LOAD_BALANCE</loadBalanceStrategy>
            <name></name>
            <selectedRelationships>matched</selectedRelationships>
            <source>
                <groupId>8414dd68-5e91-3e41-0000-000000000000</groupId>
                <id>8494b873-005f-33d9-0000-000000000000</id>
                <type>PROCESSOR</type>
            </source>
            <zIndex>0</zIndex>
        </connections>
        <connections>
            <id>b9ca24ae-fdb6-3a9c-0000-000000000000</id>
            <parentGroupId>8414dd68-5e91-3e41-0000-000000000000</parentGroupId>
            <backPressureDataSizeThreshold>1 GB</backPressureDataSizeThreshold>
            <backPressureObjectThreshold>10000</backPressureObjectThreshold>
            <destination>
                <groupId>8414dd68-5e91-3e41-0000-000000000000</groupId>
                <id>9a5701fb-82e5-3b4e-0000-000000000000</id>
                <type>FUNNEL</type>
            </destination>
            <flowFileExpiration>0 sec</flowFileExpiration>
            <labelIndex>1</labelIndex>
            <loadBalanceCompression>DO_NOT_COMPRESS</loadBalanceCompression>
            <loadBalancePartitionAttribute></loadBalancePartitionAttribute>
            <loadBalanceStatus>LOAD_BALANCE_NOT_CONFIGURED</loadBalanceStatus>
            <loadBalanceStrategy>DO_NOT_LOAD_BALANCE</loadBalanceStrategy>
            <name></name>
            <selectedRelationships>splits</selectedRelationships>
            <source>
                <groupId>8414dd68-5e91-3e41-0000-000000000000</groupId>
                <id>204cf29a-8972-3c19-0000-000000000000</id>
                <type>PROCESSOR</type>
            </source>
            <zIndex>0</zIndex>
        </connections>
        <connections>
            <id>ba3725b2-f1b1-3901-0000-000000000000</id>
            <parentGroupId>8414dd68-5e91-3e41-0000-000000000000</parentGroupId>
            <backPressureDataSizeThreshold>1 GB</backPressureDataSizeThreshold>
            <backPressureObjectThreshold>10000</backPressureObjectThreshold>
            <destination>
                <groupId>8414dd68-5e91-3e41-0000-000000000000</groupId>
                <id>8494b873-005f-33d9-0000-000000000000</id>
                <type>PROCESSOR</type>
            </destination>
            <flowFileExpiration>0 sec</flowFileExpiration>
            <labelIndex>1</labelIndex>
            <loadBalanceCompression>DO_NOT_COMPRESS</loadBalanceCompression>
            <loadBalancePartitionAttribute></loadBalancePartitionAttribute>
            <loadBalanceStatus>LOAD_BALANCE_NOT_CONFIGURED</loadBalanceStatus>
            <loadBalanceStrategy>DO_NOT_LOAD_BALANCE</loadBalanceStrategy>
            <name></name>
            <selectedRelationships>nonzero status</selectedRelationships>
            <selectedRelationships>output stream</selectedRelationships>
            <source>
                <groupId>8414dd68-5e91-3e41-0000-000000000000</groupId>
                <id>e8752c00-55fa-3568-0000-000000000000</id>
                <type>PROCESSOR</type>
            </source>
            <zIndex>0</zIndex>
        </connections>
        <connections>
            <id>c211e354-bdd6-37ba-0000-000000000000</id>
            <parentGroupId>8414dd68-5e91-3e41-0000-000000000000</parentGroupId>
            <backPressureDataSizeThreshold>1 GB</backPressureDataSizeThreshold>
            <backPressureObjectThreshold>10000</backPressureObjectThreshold>
            <destination>
                <groupId>8414dd68-5e91-3e41-0000-000000000000</groupId>
                <id>0fecae58-a198-382f-0000-000000000000</id>
                <type>PROCESSOR</type>
            </destination>
            <flowFileExpiration>0 sec</flowFileExpiration>
            <labelIndex>1</labelIndex>
            <loadBalanceCompression>DO_NOT_COMPRESS</loadBalanceCompression>
            <loadBalancePartitionAttribute></loadBalancePartitionAttribute>
            <loadBalanceStatus>LOAD_BALANCE_NOT_CONFIGURED</loadBalanceStatus>
            <loadBalanceStrategy>DO_NOT_LOAD_BALANCE</loadBalanceStrategy>
            <name></name>
            <selectedRelationships>success</selectedRelationships>
            <source>
                <groupId>8414dd68-5e91-3e41-0000-000000000000</groupId>
                <id>2cde6220-a8ad-3ba6-0000-000000000000</id>
                <type>PROCESSOR</type>
            </source>
            <zIndex>0</zIndex>
        </connections>
        <connections>
            <id>d6bb5088-986e-396b-0000-000000000000</id>
            <parentGroupId>8414dd68-5e91-3e41-0000-000000000000</parentGroupId>
            <backPressureDataSizeThreshold>1 GB</backPressureDataSizeThreshold>
            <backPressureObjectThreshold>10000</backPressureObjectThreshold>
            <destination>
                <groupId>8414dd68-5e91-3e41-0000-000000000000</groupId>
                <id>204cf29a-8972-3c19-0000-000000000000</id>
                <type>PROCESSOR</type>
            </destination>
            <flowFileExpiration>0 sec</flowFileExpiration>
            <labelIndex>1</labelIndex>
            <loadBalanceCompression>DO_NOT_COMPRESS</loadBalanceCompression>
            <loadBalancePartitionAttribute></loadBalancePartitionAttribute>
            <loadBalanceStatus>LOAD_BALANCE_NOT_CONFIGURED</loadBalanceStatus>
            <loadBalanceStrategy>DO_NOT_LOAD_BALANCE</loadBalanceStrategy>
            <name></name>
            <selectedRelationships>output stream</selectedRelationships>
            <source>
                <groupId>8414dd68-5e91-3e41-0000-000000000000</groupId>
                <id>22ba0944-f05e-3ddf-0000-000000000000</id>
                <type>PROCESSOR</type>
            </source>
            <zIndex>0</zIndex>
        </connections>
        <funnels>
            <id>9a5701fb-82e5-3b4e-0000-000000000000</id>
            <parentGroupId>8414dd68-5e91-3e41-0000-000000000000</parentGroupId>
            <position>
                <x>272.762275298541</x>
                <y>1708.468900073056</y>
            </position>
        </funnels>
        <funnels>
            <id>a21aca55-f7be-31ea-0000-000000000000</id>
            <parentGroupId>8414dd68-5e91-3e41-0000-000000000000</parentGroupId>
            <position>
                <x>281.89097034465294</x>
                <y>1026.5042556195021</y>
            </position>
        </funnels>
        <labels>
            <id>1c349e00-e914-3dc8-0000-000000000000</id>
            <parentGroupId>8414dd68-5e91-3e41-0000-000000000000</parentGroupId>
            <position>
                <x>0.0</x>
                <y>583.0551896109964</y>
            </position>
            <height>64.20708465576172</height>
            <label>stand-in for the spark job, need to test from here 
so for now, only execution code will be
 utilised as the script output is pending</label>
            <style>
                <entry>
                    <key>font-size</key>
                    <value>12px</value>
                </entry>
            </style>
            <width>303.75872802734375</width>
        </labels>
        <labels>
            <id>a641aa04-7d45-3c8a-0000-000000000000</id>
            <parentGroupId>8414dd68-5e91-3e41-0000-000000000000</parentGroupId>
            <position>
                <x>778.8213217538419</x>
                <y>929.5693977351204</y>
            </position>
            <height>28.552892684936523</height>
            <label>if the spark execution fails, we'll create a log file</label>
            <style>
                <entry>
                    <key>font-size</key>
                    <value>12px</value>
                </entry>
            </style>
            <width>287.0458068847656</width>
        </labels>
        <processors>
            <id>03374573-a857-37f2-0000-000000000000</id>
            <parentGroupId>8414dd68-5e91-3e41-0000-000000000000</parentGroupId>
            <position>
                <x>586.065806024807</x>
                <y>979.7081089629612</y>
            </position>
            <bundle>
                <artifact>nifi-update-attribute-nar</artifact>
                <group>org.apache.nifi</group>
                <version>1.8.0.3.3.1.0-10</version>
            </bundle>
            <config>
                <bulletinLevel>WARN</bulletinLevel>
                <comments></comments>
                <concurrentlySchedulableTaskCount>1</concurrentlySchedulableTaskCount>
                <descriptors>
                    <entry>
                        <key>Delete Attributes Expression</key>
                        <value>
                            <name>Delete Attributes Expression</name>
                        </value>
                    </entry>
                    <entry>
                        <key>Store State</key>
                        <value>
                            <name>Store State</name>
                        </value>
                    </entry>
                    <entry>
                        <key>Stateful Variables Initial Value</key>
                        <value>
                            <name>Stateful Variables Initial Value</name>
                        </value>
                    </entry>
                    <entry>
                        <key>filename</key>
                        <value>
                            <name>filename</name>
                        </value>
                    </entry>
                </descriptors>
                <executionNode>ALL</executionNode>
                <lossTolerant>false</lossTolerant>
                <penaltyDuration>30 sec</penaltyDuration>
                <properties>
                    <entry>
                        <key>Delete Attributes Expression</key>
                    </entry>
                    <entry>
                        <key>Store State</key>
                        <value>Do not store state</value>
                    </entry>
                    <entry>
                        <key>Stateful Variables Initial Value</key>
                    </entry>
                    <entry>
                        <key>filename</key>
                        <value>${source_system}_${country}_test_fail_${now}.log</value>
                    </entry>
                </properties>
                <runDurationMillis>0</runDurationMillis>
                <schedulingPeriod>0 sec</schedulingPeriod>
                <schedulingStrategy>TIMER_DRIVEN</schedulingStrategy>
                <yieldDuration>1 sec</yieldDuration>
            </config>
            <executionNodeRestricted>false</executionNodeRestricted>
            <name>UpdateAttribute</name>
            <relationships>
                <autoTerminate>false</autoTerminate>
                <name>success</name>
            </relationships>
            <state>STOPPED</state>
            <style/>
            <type>org.apache.nifi.processors.attributes.UpdateAttribute</type>
        </processors>
        <processors>
            <id>0fecae58-a198-382f-0000-000000000000</id>
            <parentGroupId>8414dd68-5e91-3e41-0000-000000000000</parentGroupId>
            <position>
                <x>333.143874882358</x>
                <y>240.99773600440898</y>
            </position>
            <bundle>
                <artifact>nifi-update-attribute-nar</artifact>
                <group>org.apache.nifi</group>
                <version>1.8.0.3.3.1.0-10</version>
            </bundle>
            <config>
                <bulletinLevel>WARN</bulletinLevel>
                <comments></comments>
                <concurrentlySchedulableTaskCount>1</concurrentlySchedulableTaskCount>
                <descriptors>
                    <entry>
                        <key>Delete Attributes Expression</key>
                        <value>
                            <name>Delete Attributes Expression</name>
                        </value>
                    </entry>
                    <entry>
                        <key>Store State</key>
                        <value>
                            <name>Store State</name>
                        </value>
                    </entry>
                    <entry>
                        <key>Stateful Variables Initial Value</key>
                        <value>
                            <name>Stateful Variables Initial Value</name>
                        </value>
                    </entry>
                    <entry>
                        <key>base_path</key>
                        <value>
                            <name>base_path</name>
                        </value>
                    </entry>
                    <entry>
                        <key>country</key>
                        <value>
                            <name>country</name>
                        </value>
                    </entry>
                    <entry>
                        <key>partition</key>
                        <value>
                            <name>partition</name>
                        </value>
                    </entry>
                    <entry>
                        <key>source_system</key>
                        <value>
                            <name>source_system</name>
                        </value>
                    </entry>
                </descriptors>
                <executionNode>ALL</executionNode>
                <lossTolerant>false</lossTolerant>
                <penaltyDuration>30 sec</penaltyDuration>
                <properties>
                    <entry>
                        <key>Delete Attributes Expression</key>
                    </entry>
                    <entry>
                        <key>Store State</key>
                        <value>Do not store state</value>
                    </entry>
                    <entry>
                        <key>Stateful Variables Initial Value</key>
                    </entry>
                    <entry>
                        <key>base_path</key>
                        <value>${absolute.path:substringBefore('/archival/'):substringBeforeLast('/'):substringBeforeLast('/')}</value>
                    </entry>
                    <entry>
                        <key>country</key>
                        <value>${absolute.path:substringBefore('/archival/'):substringAfterLast('/')}</value>
                    </entry>
                    <entry>
                        <key>partition</key>
                        <value>${filename:substringAfterLast("_"):substringBefore(".")}</value>
                    </entry>
                    <entry>
                        <key>source_system</key>
                        <value>${absolute.path:substringBefore('/archival/'):substringBeforeLast('/'):substringAfterLast('/')}</value>
                    </entry>
                </properties>
                <runDurationMillis>0</runDurationMillis>
                <schedulingPeriod>0 sec</schedulingPeriod>
                <schedulingStrategy>TIMER_DRIVEN</schedulingStrategy>
                <yieldDuration>1 sec</yieldDuration>
            </config>
            <executionNodeRestricted>false</executionNodeRestricted>
            <name>UpdateAttribute</name>
            <relationships>
                <autoTerminate>false</autoTerminate>
                <name>success</name>
            </relationships>
            <state>STOPPED</state>
            <style/>
            <type>org.apache.nifi.processors.attributes.UpdateAttribute</type>
        </processors>
        <processors>
            <id>204cf29a-8972-3c19-0000-000000000000</id>
            <parentGroupId>8414dd68-5e91-3e41-0000-000000000000</parentGroupId>
            <position>
                <x>123.2939370568306</x>
                <y>1417.9608716125765</y>
            </position>
            <bundle>
                <artifact>nifi-standard-nar</artifact>
                <group>org.apache.nifi</group>
                <version>1.8.0.3.3.1.0-10</version>
            </bundle>
            <config>
                <bulletinLevel>WARN</bulletinLevel>
                <comments></comments>
                <concurrentlySchedulableTaskCount>1</concurrentlySchedulableTaskCount>
                <descriptors>
                    <entry>
                        <key>Line Split Count</key>
                        <value>
                            <name>Line Split Count</name>
                        </value>
                    </entry>
                    <entry>
                        <key>Maximum Fragment Size</key>
                        <value>
                            <name>Maximum Fragment Size</name>
                        </value>
                    </entry>
                    <entry>
                        <key>Header Line Count</key>
                        <value>
                            <name>Header Line Count</name>
                        </value>
                    </entry>
                    <entry>
                        <key>Header Line Marker Characters</key>
                        <value>
                            <name>Header Line Marker Characters</name>
                        </value>
                    </entry>
                    <entry>
                        <key>Remove Trailing Newlines</key>
                        <value>
                            <name>Remove Trailing Newlines</name>
                        </value>
                    </entry>
                </descriptors>
                <executionNode>ALL</executionNode>
                <lossTolerant>false</lossTolerant>
                <penaltyDuration>30 sec</penaltyDuration>
                <properties>
                    <entry>
                        <key>Line Split Count</key>
                        <value>1</value>
                    </entry>
                    <entry>
                        <key>Maximum Fragment Size</key>
                    </entry>
                    <entry>
                        <key>Header Line Count</key>
                        <value>0</value>
                    </entry>
                    <entry>
                        <key>Header Line Marker Characters</key>
                    </entry>
                    <entry>
                        <key>Remove Trailing Newlines</key>
                        <value>true</value>
                    </entry>
                </properties>
                <runDurationMillis>0</runDurationMillis>
                <schedulingPeriod>0 sec</schedulingPeriod>
                <schedulingStrategy>TIMER_DRIVEN</schedulingStrategy>
                <yieldDuration>1 sec</yieldDuration>
            </config>
            <executionNodeRestricted>false</executionNodeRestricted>
            <name>SplitText</name>
            <relationships>
                <autoTerminate>true</autoTerminate>
                <name>failure</name>
            </relationships>
            <relationships>
                <autoTerminate>true</autoTerminate>
                <name>original</name>
            </relationships>
            <relationships>
                <autoTerminate>false</autoTerminate>
                <name>splits</name>
            </relationships>
            <state>STOPPED</state>
            <style/>
            <type>org.apache.nifi.processors.standard.SplitText</type>
        </processors>
        <processors>
            <id>22ba0944-f05e-3ddf-0000-000000000000</id>
            <parentGroupId>8414dd68-5e91-3e41-0000-000000000000</parentGroupId>
            <position>
                <x>127.16238878601371</x>
                <y>1197.1486688930102</y>
            </position>
            <bundle>
                <artifact>nifi-standard-nar</artifact>
                <group>org.apache.nifi</group>
                <version>1.8.0.3.3.1.0-10</version>
            </bundle>
            <config>
                <bulletinLevel>WARN</bulletinLevel>
                <comments></comments>
                <concurrentlySchedulableTaskCount>1</concurrentlySchedulableTaskCount>
                <descriptors>
                    <entry>
                        <key>Command Arguments</key>
                        <value>
                            <name>Command Arguments</name>
                        </value>
                    </entry>
                    <entry>
                        <key>Command Path</key>
                        <value>
                            <name>Command Path</name>
                        </value>
                    </entry>
                    <entry>
                        <key>Ignore STDIN</key>
                        <value>
                            <name>Ignore STDIN</name>
                        </value>
                    </entry>
                    <entry>
                        <key>Working Directory</key>
                        <value>
                            <name>Working Directory</name>
                        </value>
                    </entry>
                    <entry>
                        <key>Argument Delimiter</key>
                        <value>
                            <name>Argument Delimiter</name>
                        </value>
                    </entry>
                    <entry>
                        <key>Output Destination Attribute</key>
                        <value>
                            <name>Output Destination Attribute</name>
                        </value>
                    </entry>
                    <entry>
                        <key>Max Attribute Length</key>
                        <value>
                            <name>Max Attribute Length</name>
                        </value>
                    </entry>
                </descriptors>
                <executionNode>ALL</executionNode>
                <lossTolerant>false</lossTolerant>
                <penaltyDuration>30 sec</penaltyDuration>
                <properties>
                    <entry>
                        <key>Command Arguments</key>
                        <value>-p;${"base_path"};-s;${"source_system"};-c;${"country"}</value>
                    </entry>
                    <entry>
                        <key>Command Path</key>
                        <value>/tmp/file_checker.py</value>
                    </entry>
                    <entry>
                        <key>Ignore STDIN</key>
                        <value>false</value>
                    </entry>
                    <entry>
                        <key>Working Directory</key>
                        <value>/tmp</value>
                    </entry>
                    <entry>
                        <key>Argument Delimiter</key>
                        <value>;</value>
                    </entry>
                    <entry>
                        <key>Output Destination Attribute</key>
                    </entry>
                    <entry>
                        <key>Max Attribute Length</key>
                        <value>256</value>
                    </entry>
                </properties>
                <runDurationMillis>0</runDurationMillis>
                <schedulingPeriod>0 sec</schedulingPeriod>
                <schedulingStrategy>TIMER_DRIVEN</schedulingStrategy>
                <yieldDuration>1 sec</yieldDuration>
            </config>
            <executionNodeRestricted>false</executionNodeRestricted>
            <name>ExecuteStreamCommand</name>
            <relationships>
                <autoTerminate>true</autoTerminate>
                <name>nonzero status</name>
            </relationships>
            <relationships>
                <autoTerminate>true</autoTerminate>
                <name>original</name>
            </relationships>
            <relationships>
                <autoTerminate>false</autoTerminate>
                <name>output stream</name>
            </relationships>
            <state>STOPPED</state>
            <style/>
            <type>org.apache.nifi.processors.standard.ExecuteStreamCommand</type>
        </processors>
        <processors>
            <id>2cde6220-a8ad-3ba6-0000-000000000000</id>
            <parentGroupId>8414dd68-5e91-3e41-0000-000000000000</parentGroupId>
            <position>
                <x>332.8672959040623</x>
                <y>0.0</y>
            </position>
            <bundle>
                <artifact>nifi-standard-nar</artifact>
                <group>org.apache.nifi</group>
                <version>1.8.0.3.3.1.0-10</version>
            </bundle>
            <config>
                <bulletinLevel>WARN</bulletinLevel>
                <comments></comments>
                <concurrentlySchedulableTaskCount>1</concurrentlySchedulableTaskCount>
                <descriptors>
                    <entry>
                        <key>listing-strategy</key>
                        <value>
                            <name>listing-strategy</name>
                        </value>
                    </entry>
                    <entry>
                        <key>Input Directory</key>
                        <value>
                            <name>Input Directory</name>
                        </value>
                    </entry>
                    <entry>
                        <key>Recurse Subdirectories</key>
                        <value>
                            <name>Recurse Subdirectories</name>
                        </value>
                    </entry>
                    <entry>
                        <key>Input Directory Location</key>
                        <value>
                            <name>Input Directory Location</name>
                        </value>
                    </entry>
                    <entry>
                        <key>File Filter</key>
                        <value>
                            <name>File Filter</name>
                        </value>
                    </entry>
                    <entry>
                        <key>Path Filter</key>
                        <value>
                            <name>Path Filter</name>
                        </value>
                    </entry>
                    <entry>
                        <key>Include File Attributes</key>
                        <value>
                            <name>Include File Attributes</name>
                        </value>
                    </entry>
                    <entry>
                        <key>Minimum File Age</key>
                        <value>
                            <name>Minimum File Age</name>
                        </value>
                    </entry>
                    <entry>
                        <key>Maximum File Age</key>
                        <value>
                            <name>Maximum File Age</name>
                        </value>
                    </entry>
                    <entry>
                        <key>Minimum File Size</key>
                        <value>
                            <name>Minimum File Size</name>
                        </value>
                    </entry>
                    <entry>
                        <key>Maximum File Size</key>
                        <value>
                            <name>Maximum File Size</name>
                        </value>
                    </entry>
                    <entry>
                        <key>Ignore Hidden Files</key>
                        <value>
                            <name>Ignore Hidden Files</name>
                        </value>
                    </entry>
                    <entry>
                        <key>target-system-timestamp-precision</key>
                        <value>
                            <name>target-system-timestamp-precision</name>
                        </value>
                    </entry>
                    <entry>
                        <key>et-state-cache</key>
                        <value>
                            <identifiesControllerService>org.apache.nifi.distributed.cache.client.DistributedMapCacheClient</identifiesControllerService>
                            <name>et-state-cache</name>
                        </value>
                    </entry>
                    <entry>
                        <key>et-time-window</key>
                        <value>
                            <name>et-time-window</name>
                        </value>
                    </entry>
                    <entry>
                        <key>et-initial-listing-target</key>
                        <value>
                            <name>et-initial-listing-target</name>
                        </value>
                    </entry>
                    <entry>
                        <key>et-node-identifier</key>
                        <value>
                            <name>et-node-identifier</name>
                        </value>
                    </entry>
                </descriptors>
                <executionNode>PRIMARY</executionNode>
                <lossTolerant>false</lossTolerant>
                <penaltyDuration>30 sec</penaltyDuration>
                <properties>
                    <entry>
                        <key>listing-strategy</key>
                        <value>timestamps</value>
                    </entry>
                    <entry>
                        <key>Input Directory</key>
                        <value>/CTRLFW/SOURCG/SDM/DEV/sourcesystem/country/archival/</value>
                    </entry>
                    <entry>
                        <key>Recurse Subdirectories</key>
                        <value>true</value>
                    </entry>
                    <entry>
                        <key>Input Directory Location</key>
                        <value>Local</value>
                    </entry>
                    <entry>
                        <key>File Filter</key>
                        <value>.*\.ack</value>
                    </entry>
                    <entry>
                        <key>Path Filter</key>
                    </entry>
                    <entry>
                        <key>Include File Attributes</key>
                        <value>true</value>
                    </entry>
                    <entry>
                        <key>Minimum File Age</key>
                        <value>0 sec</value>
                    </entry>
                    <entry>
                        <key>Maximum File Age</key>
                    </entry>
                    <entry>
                        <key>Minimum File Size</key>
                        <value>0 B</value>
                    </entry>
                    <entry>
                        <key>Maximum File Size</key>
                    </entry>
                    <entry>
                        <key>Ignore Hidden Files</key>
                        <value>true</value>
                    </entry>
                    <entry>
                        <key>target-system-timestamp-precision</key>
                        <value>auto-detect</value>
                    </entry>
                    <entry>
                        <key>et-state-cache</key>
                    </entry>
                    <entry>
                        <key>et-time-window</key>
                        <value>3 hours</value>
                    </entry>
                    <entry>
                        <key>et-initial-listing-target</key>
                        <value>all</value>
                    </entry>
                    <entry>
                        <key>et-node-identifier</key>
                        <value>${hostname()}</value>
                    </entry>
                </properties>
                <runDurationMillis>0</runDurationMillis>
                <schedulingPeriod>0 sec</schedulingPeriod>
                <schedulingStrategy>TIMER_DRIVEN</schedulingStrategy>
                <yieldDuration>1 sec</yieldDuration>
            </config>
            <executionNodeRestricted>false</executionNodeRestricted>
            <name>ListFile</name>
            <relationships>
                <autoTerminate>false</autoTerminate>
                <name>success</name>
            </relationships>
            <state>STOPPED</state>
            <style/>
            <type>org.apache.nifi.processors.standard.ListFile</type>
        </processors>
        <processors>
            <id>8494b873-005f-33d9-0000-000000000000</id>
            <parentGroupId>8414dd68-5e91-3e41-0000-000000000000</parentGroupId>
            <position>
                <x>342.0574628316872</x>
                <y>757.9835656534245</y>
            </position>
            <bundle>
                <artifact>nifi-standard-nar</artifact>
                <group>org.apache.nifi</group>
                <version>1.8.0.3.3.1.0-10</version>
            </bundle>
            <config>
                <bulletinLevel>WARN</bulletinLevel>
                <comments></comments>
                <concurrentlySchedulableTaskCount>1</concurrentlySchedulableTaskCount>
                <descriptors>
                    <entry>
                        <key>Routing Strategy</key>
                        <value>
                            <name>Routing Strategy</name>
                        </value>
                    </entry>
                    <entry>
                        <key>successful_operation</key>
                        <value>
                            <name>successful_operation</name>
                        </value>
                    </entry>
                </descriptors>
                <executionNode>ALL</executionNode>
                <lossTolerant>false</lossTolerant>
                <penaltyDuration>30 sec</penaltyDuration>
                <properties>
                    <entry>
                        <key>Routing Strategy</key>
                        <value>Route to 'match' if all match</value>
                    </entry>
                    <entry>
                        <key>successful_operation</key>
                        <value>${execution.status:equals(0)}</value>
                    </entry>
                </properties>
                <runDurationMillis>0</runDurationMillis>
                <schedulingPeriod>0 sec</schedulingPeriod>
                <schedulingStrategy>TIMER_DRIVEN</schedulingStrategy>
                <yieldDuration>1 sec</yieldDuration>
            </config>
            <executionNodeRestricted>false</executionNodeRestricted>
            <name>RouteOnAttribute</name>
            <relationships>
                <autoTerminate>false</autoTerminate>
                <name>matched</name>
            </relationships>
            <relationships>
                <autoTerminate>false</autoTerminate>
                <name>unmatched</name>
            </relationships>
            <state>STOPPED</state>
            <style/>
            <type>org.apache.nifi.processors.standard.RouteOnAttribute</type>
        </processors>
        <processors>
            <id>b41c46dd-d05f-3ce1-0000-000000000000</id>
            <parentGroupId>8414dd68-5e91-3e41-0000-000000000000</parentGroupId>
            <position>
                <x>590.5228897455513</x>
                <y>1227.0591067856535</y>
            </position>
            <bundle>
                <artifact>nifi-standard-nar</artifact>
                <group>org.apache.nifi</group>
                <version>1.8.0.3.3.1.0-10</version>
            </bundle>
            <config>
                <bulletinLevel>WARN</bulletinLevel>
                <comments></comments>
                <concurrentlySchedulableTaskCount>1</concurrentlySchedulableTaskCount>
                <descriptors>
                    <entry>
                        <key>Directory</key>
                        <value>
                            <name>Directory</name>
                        </value>
                    </entry>
                    <entry>
                        <key>Conflict Resolution Strategy</key>
                        <value>
                            <name>Conflict Resolution Strategy</name>
                        </value>
                    </entry>
                    <entry>
                        <key>Create Missing Directories</key>
                        <value>
                            <name>Create Missing Directories</name>
                        </value>
                    </entry>
                    <entry>
                        <key>Maximum File Count</key>
                        <value>
                            <name>Maximum File Count</name>
                        </value>
                    </entry>
                    <entry>
                        <key>Last Modified Time</key>
                        <value>
                            <name>Last Modified Time</name>
                        </value>
                    </entry>
                    <entry>
                        <key>Permissions</key>
                        <value>
                            <name>Permissions</name>
                        </value>
                    </entry>
                    <entry>
                        <key>Owner</key>
                        <value>
                            <name>Owner</name>
                        </value>
                    </entry>
                    <entry>
                        <key>Group</key>
                        <value>
                            <name>Group</name>
                        </value>
                    </entry>
                </descriptors>
                <executionNode>ALL</executionNode>
                <lossTolerant>false</lossTolerant>
                <penaltyDuration>30 sec</penaltyDuration>
                <properties>
                    <entry>
                        <key>Directory</key>
                        <value>/tmp/</value>
                    </entry>
                    <entry>
                        <key>Conflict Resolution Strategy</key>
                        <value>fail</value>
                    </entry>
                    <entry>
                        <key>Create Missing Directories</key>
                        <value>true</value>
                    </entry>
                    <entry>
                        <key>Maximum File Count</key>
                    </entry>
                    <entry>
                        <key>Last Modified Time</key>
                    </entry>
                    <entry>
                        <key>Permissions</key>
                        <value>755</value>
                    </entry>
                    <entry>
                        <key>Owner</key>
                    </entry>
                    <entry>
                        <key>Group</key>
                    </entry>
                </properties>
                <runDurationMillis>0</runDurationMillis>
                <schedulingPeriod>0 sec</schedulingPeriod>
                <schedulingStrategy>TIMER_DRIVEN</schedulingStrategy>
                <yieldDuration>1 sec</yieldDuration>
            </config>
            <executionNodeRestricted>false</executionNodeRestricted>
            <name>PutFile</name>
            <relationships>
                <autoTerminate>true</autoTerminate>
                <name>failure</name>
            </relationships>
            <relationships>
                <autoTerminate>true</autoTerminate>
                <name>success</name>
            </relationships>
            <state>STOPPED</state>
            <style/>
            <type>org.apache.nifi.processors.standard.PutFile</type>
        </processors>
        <processors>
            <id>e8752c00-55fa-3568-0000-000000000000</id>
            <parentGroupId>8414dd68-5e91-3e41-0000-000000000000</parentGroupId>
            <position>
                <x>337.32407091491996</x>
                <y>469.0755359012194</y>
            </position>
            <bundle>
                <artifact>nifi-standard-nar</artifact>
                <group>org.apache.nifi</group>
                <version>1.8.0.3.3.1.0-10</version>
            </bundle>
            <config>
                <bulletinLevel>WARN</bulletinLevel>
                <comments></comments>
                <concurrentlySchedulableTaskCount>1</concurrentlySchedulableTaskCount>
                <descriptors>
                    <entry>
                        <key>Command Arguments</key>
                        <value>
                            <name>Command Arguments</name>
                        </value>
                    </entry>
                    <entry>
                        <key>Command Path</key>
                        <value>
                            <name>Command Path</name>
                        </value>
                    </entry>
                    <entry>
                        <key>Ignore STDIN</key>
                        <value>
                            <name>Ignore STDIN</name>
                        </value>
                    </entry>
                    <entry>
                        <key>Working Directory</key>
                        <value>
                            <name>Working Directory</name>
                        </value>
                    </entry>
                    <entry>
                        <key>Argument Delimiter</key>
                        <value>
                            <name>Argument Delimiter</name>
                        </value>
                    </entry>
                    <entry>
                        <key>Output Destination Attribute</key>
                        <value>
                            <name>Output Destination Attribute</name>
                        </value>
                    </entry>
                    <entry>
                        <key>Max Attribute Length</key>
                        <value>
                            <name>Max Attribute Length</name>
                        </value>
                    </entry>
                </descriptors>
                <executionNode>PRIMARY</executionNode>
                <lossTolerant>false</lossTolerant>
                <penaltyDuration>30 sec</penaltyDuration>
                <properties>
                    <entry>
                        <key>Command Arguments</key>
                        <value>${"source_system"};${"country"};${"base_path"};"sri_open,sri_nonopen"</value>
                    </entry>
                    <entry>
                        <key>Command Path</key>
                        <value>/CTRLFW/SOURCG/SDM/DEV/deployment/1.3.1/scripts/sdm-tokenization-util.sh</value>
                    </entry>
                    <entry>
                        <key>Ignore STDIN</key>
                        <value>false</value>
                    </entry>
                    <entry>
                        <key>Working Directory</key>
                        <value>/CTRLFW/SOURCG/SDM/DEV/deployment/1.3.1/scripts/</value>
                    </entry>
                    <entry>
                        <key>Argument Delimiter</key>
                        <value>;</value>
                    </entry>
                    <entry>
                        <key>Output Destination Attribute</key>
                    </entry>
                    <entry>
                        <key>Max Attribute Length</key>
                        <value>256</value>
                    </entry>
                </properties>
                <runDurationMillis>0</runDurationMillis>
                <schedulingPeriod>0 sec</schedulingPeriod>
                <schedulingStrategy>TIMER_DRIVEN</schedulingStrategy>
                <yieldDuration>1 sec</yieldDuration>
            </config>
            <executionNodeRestricted>false</executionNodeRestricted>
            <name>ExecuteStreamCommand</name>
            <relationships>
                <autoTerminate>false</autoTerminate>
                <name>nonzero status</name>
            </relationships>
            <relationships>
                <autoTerminate>true</autoTerminate>
                <name>original</name>
            </relationships>
            <relationships>
                <autoTerminate>false</autoTerminate>
                <name>output stream</name>
            </relationships>
            <state>STOPPED</state>
            <style/>
            <type>org.apache.nifi.processors.standard.ExecuteStreamCommand</type>
        </processors>
    </snippet>
    <timestamp>11/14/2021 22:21:48 UTC</timestamp>
</template>
